spectroapi/__init__.py
spectroapi/identify.py
spectroapi-0.1.7.dist-info/METADATA
spectroapi-0.1.7.dist-info/WHEEL
spectroapi-0.1.7.dist-info/top_level.txt
spectroapi-0.1.7.dist-info/RECORD
