Metadata-Version: 2.4
Name: spectroapi
Version: 0.1.7
Summary: A discord bot IOS status
Author-email: Spectro <spectro5678@gmail.coom>
License: MIT
Project-URL: Homepage, https://xvz.bot
Project-URL: Source, https://github.com/user9884993499999189
Requires-Python: >=3.8
Requires-Dist: discord.py>=2.0.0
